{"0000":{"zip_code":"1030000","prefecture":"東京都","prefecture_kana":"トウキョウト","city":"中央区","city_kana":"チュウオウク","town":"","town_kana":"","prefecture_code":13},"0027":{"zip_code":"1030027","prefecture":"東京都","prefecture_kana":"トウキョウト","city":"中央区","city_kana":"チュウオウク","town":"日本橋","town_kana":"ニホンバシ","prefecture_code":13},"0011":{"zip_code":"1030011","prefecture":"東京都","prefecture_kana":"トウキョウト","city":"中央区","city_kana":"チュウオウク","town":"日本橋大伝馬町","town_kana":"ニホンバシオオデンマチョウ","prefecture_code":13},"0014":{"zip_code":"1030014","prefecture":"東京都","prefecture_kana":"トウキョウト","city":"中央区","city_kana":"チュウオウク","town":"日本橋蛎殻町","town_kana":"ニホンバシカキガラチョウ","prefecture_code":13},"0026":{"zip_code":"1030026","prefecture":"東京都","prefecture_kana":"トウキョウト","city":"中央区","city_kana":"チュウオウク","town":"日本橋兜町","town_kana":"ニホンバシカブトチョウ","prefecture_code":13},"0025":{"zip_code":"1030025","prefecture":"東京都","prefecture_kana":"トウキョウト","city":"中央区","city_kana":"チュウオウク","town":"日本橋茅場町","town_kana":"ニホンバシカヤバチョウ","prefecture_code":13},"0016":{"zip_code":"1030016","prefecture":"東京都","prefecture_kana":"トウキョウト","city":"中央区","city_kana":"チュウオウク","town":"日本橋小網町","town_kana":"ニホンバシコアミチョウ","prefecture_code":13},"0001":{"zip_code":"1030001","prefecture":"東京都","prefecture_kana":"トウキョウト","city":"中央区","city_kana":"チュウオウク","town":"日本橋小伝馬町","town_kana":"ニホンバシコデンマチョウ","prefecture_code":13},"0024":{"zip_code":"1030024","prefecture":"東京都","prefecture_kana":"トウキョウト","city":"中央区","city_kana":"チュウオウク","town":"日本橋小舟町","town_kana":"ニホンバシコブナチョウ","prefecture_code":13},"0006":{"zip_code":"1030006","prefecture":"東京都","prefecture_kana":"トウキョウト","city":"中央区","city_kana":"チュウオウク","town":"日本橋富沢町","town_kana":"ニホンバシトミザワチョウ","prefecture_code":13},"0008":{"zip_code":"1030008","prefecture":"東京都","prefecture_kana":"トウキョウト","city":"中央区","city_kana":"チュウオウク","town":"日本橋中洲","town_kana":"ニホンバシナカス","prefecture_code":13},"0013":{"zip_code":"1030013","prefecture":"東京都","prefecture_kana":"トウキョウト","city":"中央区","city_kana":"チュウオウク","town":"日本橋人形町","town_kana":"ニホンバシニンギョウチョウ","prefecture_code":13},"0015":{"zip_code":"1030015","prefecture":"東京都","prefecture_kana":"トウキョウト","city":"中央区","city_kana":"チュウオウク","town":"日本橋箱崎町","town_kana":"ニホンバシハコザキチョウ","prefecture_code":13},"0007":{"zip_code":"1030007","prefecture":"東京都","prefecture_kana":"トウキョウト","city":"中央区","city_kana":"チュウオウク","town":"日本橋浜町","town_kana":"ニホンバシハマチョウ","prefecture_code":13},"0002":{"zip_code":"1030002","prefecture":"東京都","prefecture_kana":"トウキョウト","city":"中央区","city_kana":"チュウオウク","town":"日本橋馬喰町","town_kana":"ニホンバシバクロチョウ","prefecture_code":13},"0005":{"zip_code":"1030005","prefecture":"東京都","prefecture_kana":"トウキョウト","city":"中央区","city_kana":"チュウオウク","town":"日本橋久松町","town_kana":"ニホンバシヒサマツチョウ","prefecture_code":13},"0012":{"zip_code":"1030012","prefecture":"東京都","prefecture_kana":"トウキョウト","city":"中央区","city_kana":"チュウオウク","town":"日本橋堀留町","town_kana":"ニホンバシホリドメチョウ","prefecture_code":13},"0021":{"zip_code":"1030021","prefecture":"東京都","prefecture_kana":"トウキョウト","city":"中央区","city_kana":"チュウオウク","town":"日本橋本石町","town_kana":"ニホンバシホンゴクチョウ","prefecture_code":13},"0023":{"zip_code":"1030023","prefecture":"東京都","prefecture_kana":"トウキョウト","city":"中央区","city_kana":"チュウオウク","town":"日本橋本町","town_kana":"ニホンバシホンチョウ","prefecture_code":13},"0022":{"zip_code":"1030022","prefecture":"東京都","prefecture_kana":"トウキョウト","city":"中央区","city_kana":"チュウオウク","town":"日本橋室町","town_kana":"ニホンバシムロマチ","prefecture_code":13},"0003":{"zip_code":"1030003","prefecture":"東京都","prefecture_kana":"トウキョウト","city":"中央区","city_kana":"チュウオウク","town":"日本橋横山町","town_kana":"ニホンバシヨコヤマチョウ","prefecture_code":13},"0004":{"zip_code":"1030004","prefecture":"東京都","prefecture_kana":"トウキョウト","city":"中央区","city_kana":"チュウオウク","town":"東日本橋","town_kana":"ヒガシニホンバシ","prefecture_code":13},"0028":{"zip_code":"1030028","prefecture":"東京都","prefecture_kana":"トウキョウト","city":"中央区","city_kana":"チュウオウク","town":"八重洲","town_kana":"ヤエス","prefecture_code":13}}