{"0000":{"zip_code":"6980000","prefecture":"島根県","prefecture_kana":"シマネケン","city":"益田市","city_kana":"マスダシ","town":"","town_kana":"","prefecture_code":32},"0034":{"zip_code":"6980034","prefecture":"島根県","prefecture_kana":"シマネケン","city":"益田市","city_kana":"マスダシ","town":"赤城町","town_kana":"アカギチョウ","prefecture_code":32},"0027":{"zip_code":"6980027","prefecture":"島根県","prefecture_kana":"シマネケン","city":"益田市","city_kana":"マスダシ","town":"あけぼの東町","town_kana":"アケボノヒガシマチ","prefecture_code":32},"0025":{"zip_code":"6980025","prefecture":"島根県","prefecture_kana":"シマネケン","city":"益田市","city_kana":"マスダシ","town":"あけぼの西町","town_kana":"アケボノニシマチ","prefecture_code":32},"0026":{"zip_code":"6980026","prefecture":"島根県","prefecture_kana":"シマネケン","city":"益田市","city_kana":"マスダシ","town":"あけぼの本町","town_kana":"アケボノホンマチ","prefecture_code":32},"2253":{"zip_code":"6982253","prefecture":"島根県","prefecture_kana":"シマネケン","city":"益田市","city_kana":"マスダシ","town":"愛栄町","town_kana":"アサカチョウ","prefecture_code":32},"0022":{"zip_code":"6980022","prefecture":"島根県","prefecture_kana":"シマネケン","city":"益田市","city_kana":"マスダシ","town":"有明町","town_kana":"アリアケチョウ","prefecture_code":32},"0037":{"zip_code":"6980037","prefecture":"島根県","prefecture_kana":"シマネケン","city":"益田市","city_kana":"マスダシ","town":"飯田町","town_kana":"イイダチョウ","prefecture_code":32},"2142":{"zip_code":"6982142","prefecture":"島根県","prefecture_kana":"シマネケン","city":"益田市","city_kana":"マスダシ","town":"市原町","town_kana":"イチハラチョウ","prefecture_code":32},"0014":{"zip_code":"6980014","prefecture":"島根県","prefecture_kana":"シマネケン","city":"益田市","city_kana":"マスダシ","town":"岩倉町","town_kana":"イワクラチョウ","prefecture_code":32},"0051":{"zip_code":"6980051","prefecture":"島根県","prefecture_kana":"シマネケン","city":"益田市","city_kana":"マスダシ","town":"内田町","town_kana":"ウチダチョウ","prefecture_code":32},"2143":{"zip_code":"6982143","prefecture":"島根県","prefecture_kana":"シマネケン","city":"益田市","city_kana":"マスダシ","town":"内田町","town_kana":"ウチダチョウ","prefecture_code":32},"0413":{"zip_code":"6980413","prefecture":"島根県","prefecture_kana":"シマネケン","city":"益田市","city_kana":"マスダシ","town":"馬谷町","town_kana":"ウマダニチョウ","prefecture_code":32},"0024":{"zip_code":"6980024","prefecture":"島根県","prefecture_kana":"シマネケン","city":"益田市","city_kana":"マスダシ","town":"駅前町","town_kana":"エキマエチョウ","prefecture_code":32},"0012":{"zip_code":"6980012","prefecture":"島根県","prefecture_kana":"シマネケン","city":"益田市","city_kana":"マスダシ","town":"大谷町","town_kana":"オオタニチョウ","prefecture_code":32},"0003":{"zip_code":"6980003","prefecture":"島根県","prefecture_kana":"シマネケン","city":"益田市","city_kana":"マスダシ","town":"乙吉町","town_kana":"オトヨシチョウ","prefecture_code":32},"2252":{"zip_code":"6982252","prefecture":"島根県","prefecture_kana":"シマネケン","city":"益田市","city_kana":"マスダシ","town":"柏原町","town_kana":"カシバラチョウ","prefecture_code":32},"2254":{"zip_code":"6982254","prefecture":"島根県","prefecture_kana":"シマネケン","city":"益田市","city_kana":"マスダシ","town":"桂平町","town_kana":"カツラヒラチョウ","prefecture_code":32},"2255":{"zip_code":"6982255","prefecture":"島根県","prefecture_kana":"シマネケン","city":"益田市","city_kana":"マスダシ","town":"上黒谷町","town_kana":"カミクロダニチョウ","prefecture_code":32},"2145":{"zip_code":"6982145","prefecture":"島根県","prefecture_kana":"シマネケン","city":"益田市","city_kana":"マスダシ","town":"川登町","town_kana":"カワノボリチョウ","prefecture_code":32},"0013":{"zip_code":"6980013","prefecture":"島根県","prefecture_kana":"シマネケン","city":"益田市","city_kana":"マスダシ","town":"久々茂町","town_kana":"ククモチョウ","prefecture_code":32},"0001":{"zip_code":"6980001","prefecture":"島根県","prefecture_kana":"シマネケン","city":"益田市","city_kana":"マスダシ","town":"久城町","town_kana":"クシロチョウ","prefecture_code":32},"2251":{"zip_code":"6982251","prefecture":"島根県","prefecture_kana":"シマネケン","city":"益田市","city_kana":"マスダシ","town":"黒周町","town_kana":"クロスチョウ","prefecture_code":32},"0021":{"zip_code":"6980021","prefecture":"島根県","prefecture_kana":"シマネケン","city":"益田市","city_kana":"マスダシ","town":"幸町","town_kana":"サイワイチョウ","prefecture_code":32},"0035":{"zip_code":"6980035","prefecture":"島根県","prefecture_kana":"シマネケン","city":"益田市","city_kana":"マスダシ","town":"栄町","town_kana":"サカエマチ","prefecture_code":32},"0414":{"zip_code":"6980414","prefecture":"島根県","prefecture_kana":"シマネケン","city":"益田市","city_kana":"マスダシ","town":"下波田町","town_kana":"シモハダチョウ","prefecture_code":32},"0002":{"zip_code":"6980002","prefecture":"島根県","prefecture_kana":"シマネケン","city":"益田市","city_kana":"マスダシ","town":"下本郷町","town_kana":"シモホンゴウチョウ","prefecture_code":32},"0007":{"zip_code":"6980007","prefecture":"島根県","prefecture_kana":"シマネケン","city":"益田市","city_kana":"マスダシ","town":"昭和町","town_kana":"ショウワチョウ","prefecture_code":32},"2141":{"zip_code":"6982141","prefecture":"島根県","prefecture_kana":"シマネケン","city":"益田市","city_kana":"マスダシ","town":"白上町","town_kana":"シラカミチョウ","prefecture_code":32},"0036":{"zip_code":"6980036","prefecture":"島根県","prefecture_kana":"シマネケン","city":"益田市","city_kana":"マスダシ","town":"須子町","town_kana":"スコチョウ","prefecture_code":32},"0011":{"zip_code":"6980011","prefecture":"島根県","prefecture_kana":"シマネケン","city":"益田市","city_kana":"マスダシ","town":"染羽町","town_kana":"ソメバチョウ","prefecture_code":32},"0041":{"zip_code":"6980041","prefecture":"島根県","prefecture_kana":"シマネケン","city":"益田市","city_kana":"マスダシ","town":"高津町","town_kana":"タカツチョウ","prefecture_code":32},"0031":{"zip_code":"6980031","prefecture":"島根県","prefecture_kana":"シマネケン","city":"益田市","city_kana":"マスダシ","town":"多田町","town_kana":"タダチョウ","prefecture_code":32},"0016":{"zip_code":"6980016","prefecture":"島根県","prefecture_kana":"シマネケン","city":"益田市","city_kana":"マスダシ","town":"土井町","town_kana":"ドイチョウ","prefecture_code":32},"0023":{"zip_code":"6980023","prefecture":"島根県","prefecture_kana":"シマネケン","city":"益田市","city_kana":"マスダシ","town":"常盤町","town_kana":"トキワチョウ","prefecture_code":32},"0015":{"zip_code":"6980015","prefecture":"島根県","prefecture_kana":"シマネケン","city":"益田市","city_kana":"マスダシ","town":"栃山町","town_kana":"トチヤマチョウ","prefecture_code":32},"2146":{"zip_code":"6982146","prefecture":"島根県","prefecture_kana":"シマネケン","city":"益田市","city_kana":"マスダシ","town":"中垣内町","town_kana":"ナカガウチチョウ","prefecture_code":32},"0044":{"zip_code":"6980044","prefecture":"島根県","prefecture_kana":"シマネケン","city":"益田市","city_kana":"マスダシ","town":"中須町","town_kana":"ナカズチョウ","prefecture_code":32},"0043":{"zip_code":"6980043","prefecture":"島根県","prefecture_kana":"シマネケン","city":"益田市","city_kana":"マスダシ","town":"中島町","town_kana":"ナカノシマチョウ","prefecture_code":32},"0042":{"zip_code":"6980042","prefecture":"島根県","prefecture_kana":"シマネケン","city":"益田市","city_kana":"マスダシ","town":"中吉田町","town_kana":"ナカヨシダチョウ","prefecture_code":32},"0412":{"zip_code":"6980412","prefecture":"島根県","prefecture_kana":"シマネケン","city":"益田市","city_kana":"マスダシ","town":"長沢町","town_kana":"ナガサワチョウ","prefecture_code":32},"0017":{"zip_code":"6980017","prefecture":"島根県","prefecture_kana":"シマネケン","city":"益田市","city_kana":"マスダシ","town":"七尾町","town_kana":"ナナオチョウ","prefecture_code":32},"0411":{"zip_code":"6980411","prefecture":"島根県","prefecture_kana":"シマネケン","city":"益田市","city_kana":"マスダシ","town":"波田町","town_kana":"ハダチョウ","prefecture_code":32},"0004":{"zip_code":"6980004","prefecture":"島根県","prefecture_kana":"シマネケン","city":"益田市","city_kana":"マスダシ","town":"東町","town_kana":"ヒガシマチ","prefecture_code":32},"1223":{"zip_code":"6981223","prefecture":"島根県","prefecture_kana":"シマネケン","city":"益田市","city_kana":"マスダシ","town":"匹見町石谷","town_kana":"ヒキミチョウイシタニ","prefecture_code":32},"1213":{"zip_code":"6981213","prefecture":"島根県","prefecture_kana":"シマネケン","city":"益田市","city_kana":"マスダシ","town":"匹見町落合","town_kana":"ヒキミチョウオチアイ","prefecture_code":32},"1212":{"zip_code":"6981212","prefecture":"島根県","prefecture_kana":"シマネケン","city":"益田市","city_kana":"マスダシ","town":"匹見町紙祖","town_kana":"ヒキミチョウシソ","prefecture_code":32},"1221":{"zip_code":"6981221","prefecture":"島根県","prefecture_kana":"シマネケン","city":"益田市","city_kana":"マスダシ","town":"匹見町澄川","town_kana":"ヒキミチョウスミカワ","prefecture_code":32},"1211":{"zip_code":"6981211","prefecture":"島根県","prefecture_kana":"シマネケン","city":"益田市","city_kana":"マスダシ","town":"匹見町匹見","town_kana":"ヒキミチョウヒキミ","prefecture_code":32},"1222":{"zip_code":"6981222","prefecture":"島根県","prefecture_kana":"シマネケン","city":"益田市","city_kana":"マスダシ","town":"匹見町広瀬","town_kana":"ヒキミチョウヒロセ","prefecture_code":32},"1201":{"zip_code":"6981201","prefecture":"島根県","prefecture_kana":"シマネケン","city":"益田市","city_kana":"マスダシ","town":"匹見町道川","town_kana":"ヒキミチョウミチカワ","prefecture_code":32},"0005":{"zip_code":"6980005","prefecture":"島根県","prefecture_kana":"シマネケン","city":"益田市","city_kana":"マスダシ","town":"本町","town_kana":"ホンマチ","prefecture_code":32},"0032":{"zip_code":"6980032","prefecture":"島根県","prefecture_kana":"シマネケン","city":"益田市","city_kana":"マスダシ","town":"水分町","town_kana":"ミズワケチョウ","prefecture_code":32},"0213":{"zip_code":"6980213","prefecture":"島根県","prefecture_kana":"シマネケン","city":"益田市","city_kana":"マスダシ","town":"美都町朝倉","town_kana":"ミトチョウアサクラ","prefecture_code":32},"0201":{"zip_code":"6980201","prefecture":"島根県","prefecture_kana":"シマネケン","city":"益田市","city_kana":"マスダシ","town":"美都町板井川","town_kana":"ミトチョウイタイガワ","prefecture_code":32},"0202":{"zip_code":"6980202","prefecture":"島根県","prefecture_kana":"シマネケン","city":"益田市","city_kana":"マスダシ","town":"美都町宇津川","town_kana":"ミトチョウウヅカワ","prefecture_code":32},"0206":{"zip_code":"6980206","prefecture":"島根県","prefecture_kana":"シマネケン","city":"益田市","city_kana":"マスダシ","town":"美都町久原","town_kana":"ミトチョウクバラ","prefecture_code":32},"0211":{"zip_code":"6980211","prefecture":"島根県","prefecture_kana":"シマネケン","city":"益田市","city_kana":"マスダシ","town":"美都町小原","town_kana":"ミトチョウコバラ","prefecture_code":32},"0214":{"zip_code":"6980214","prefecture":"島根県","prefecture_kana":"シマネケン","city":"益田市","city_kana":"マスダシ","town":"美都町笹倉","town_kana":"ミトチョウササクラ","prefecture_code":32},"0212":{"zip_code":"6980212","prefecture":"島根県","prefecture_kana":"シマネケン","city":"益田市","city_kana":"マスダシ","town":"美都町仙道","town_kana":"ミトチョウセンドウ","prefecture_code":32},"0203":{"zip_code":"6980203","prefecture":"島根県","prefecture_kana":"シマネケン","city":"益田市","city_kana":"マスダシ","town":"美都町都茂","town_kana":"ミトチョウツモ","prefecture_code":32},"0207":{"zip_code":"6980207","prefecture":"島根県","prefecture_kana":"シマネケン","city":"益田市","city_kana":"マスダシ","town":"美都町丸茂","town_kana":"ミトチョウマルモ","prefecture_code":32},"0205":{"zip_code":"6980205","prefecture":"島根県","prefecture_kana":"シマネケン","city":"益田市","city_kana":"マスダシ","town":"美都町三谷","town_kana":"ミトチョウミタニ","prefecture_code":32},"0204":{"zip_code":"6980204","prefecture":"島根県","prefecture_kana":"シマネケン","city":"益田市","city_kana":"マスダシ","town":"美都町山本","town_kana":"ミトチョウヤマモト","prefecture_code":32},"0006":{"zip_code":"6980006","prefecture":"島根県","prefecture_kana":"シマネケン","city":"益田市","city_kana":"マスダシ","town":"三宅町","town_kana":"ミヤケチョウ","prefecture_code":32},"2144":{"zip_code":"6982144","prefecture":"島根県","prefecture_kana":"シマネケン","city":"益田市","city_kana":"マスダシ","town":"虫追町","town_kana":"ムソウチョウ","prefecture_code":32},"0033":{"zip_code":"6980033","prefecture":"島根県","prefecture_kana":"シマネケン","city":"益田市","city_kana":"マスダシ","town":"元町","town_kana":"モトマチ","prefecture_code":32}}